{
  "title": "Nate the Great: The Fleeing Fang",
  "author": "Marjorie Weinman Sharmat",
  "genre": "Mystery",
  "book_level": {
    "grade": 2,
    "description": "Early reader level - simple mystery about a detective solving a case"
  },
  "total_questions": 20,
  "questions": [
    {"id": 1, "difficulty": "easy", "question": "What is the main character's name?", "options": {"A": "Nate the Great, a young detective", "B": "Sludge, the mystery solver", "C": "Fang, the brave dog hero", "D": "Rosamond, the cat lover"}, "answer": "A", "explanation": "The main character introduces himself as Nate the Great, a detective."},
    {"id": 2, "difficulty": "easy", "question": "What is the name of Nate's dog?", "options": {"A": "Fang, Annie's big dog", "B": "Sludge, his detective partner", "C": "Pip, the small helper dog", "D": "Hex, Rosamond's favorite"}, "answer": "B", "explanation": "Nate's dog is named Sludge, and he is also a detective."},
    {"id": 3, "difficulty": "easy", "question": "Why are Nate's friends throwing him a party?", "options": {"A": "It's his special birthday today", "B": "He is moving far away soon", "C": "He solved many cases for them", "D": "He won a big detective prize"}, "answer": "C", "explanation": "They are having a Detective Party because Nate has solved so many cases for them."},
    {"id": 4, "difficulty": "easy", "question": "Whose dog ran away before the party?", "options": {"A": "Nate's dog ran away first", "B": "Oliver's pet escaped the yard", "C": "Rosamond's dog disappeared", "D": "Annie's dog Fang ran off"}, "answer": "D", "explanation": "Fang is Annie's dog, and he ran away before the party."},
    {"id": 5, "difficulty": "easy", "question": "What food does Nate love to eat the most?", "options": {"A": "He loves eating warm pancakes", "B": "He enjoys pizza every day", "C": "He likes chocolate ice cream", "D": "He prefers cookies and milk"}, "answer": "A", "explanation": "Nate the Great loves pancakes. Pancakes help him think."},
    {"id": 6, "difficulty": "easy", "question": "How many cats does Rosamond have?", "options": {"A": "She has two small cats", "B": "She owns four Hex cats", "C": "She keeps three black cats", "D": "She has five fluffy cats"}, "answer": "B", "explanation": "Rosamond has four cats: Super Hex, Big Hex, Little Hex, and Plain Hex."},
    {"id": 7, "difficulty": "easy", "question": "What did Annie do to clean Fang instead of giving him a bath?", "options": {"A": "She brushed him with a comb", "B": "She wiped him with wet towels", "C": "She feather-dusted him quickly", "D": "She used a vacuum cleaner"}, "answer": "C", "explanation": "Annie didn't have time for a bath, so she feather-dusted Fang."},
    {"id": 8, "difficulty": "medium", "question": "When the two tiny poodles barked at Fang, he ran away because...", "options": {"A": "he was very scared of tiny dogs", "B": "he wanted to chase them around", "C": "Annie accidentally said the word bark", "D": "he smelled some food nearby"}, "answer": "C", "explanation": "When Annie said 'bark, bark, bark' to shoo the poodles, Fang thought it was a command because 'bark' rhymes with 'park' in his training."},
    {"id": 9, "difficulty": "medium", "question": "Annie trained Fang using a rhyming book, but Fang mixed up the commands so...", "options": {"A": "he did nothing when she spoke", "B": "he did the rhyming line instead", "C": "he barked at her all the time", "D": "he always ran away from her"}, "answer": "B", "explanation": "When Annie said one line, Fang did the other rhyming line instead, so she had to say them backwards."},
    {"id": 10, "difficulty": "medium", "question": "The lady with the green hat might be a 'red herring' which means...", "options": {"A": "she sells fish at the market", "B": "she wears red clothes usually", "C": "she is a dangerous criminal", "D": "she seems like a clue but isn't"}, "answer": "D", "explanation": "Nate explains a red herring is something that 'seems like a clue but isn't a clue.'"},
    {"id": 11, "difficulty": "medium", "question": "Pip saw Fang following a lady in a green hat, but this was...", "options": {"A": "not the real reason he left", "B": "exactly where Fang wanted to go", "C": "the place where Fang now lives", "D": "completely made up by Pip"}, "answer": "A", "explanation": "Although Fang was seen behind the lady, he wasn't really following her - he was going to the park."},
    {"id": 12, "difficulty": "medium", "question": "Nate figured out the real clue when Sludge started...", "options": {"A": "barking loudly at the front door", "B": "licking ice cream off the table", "C": "running in circles on the floor", "D": "hiding under the bed in fear"}, "answer": "B", "explanation": "When Sludge licked the dripping ice cream, Nate remembered the rhyme 'lick, lick, lick' and realized the answer."},
    {"id": 13, "difficulty": "medium", "question": "Nate says the first step to finding something missing is to...", "options": {"A": "call the police right away", "B": "give up and stop looking", "C": "remember what was different", "D": "ask everyone you can find"}, "answer": "C", "explanation": "Nate tells Annie to 'remember if there was anything different' and 'where you last saw him.'"},
    {"id": 14, "difficulty": "medium", "question": "Where did Nate finally find Fang sleeping?", "options": {"A": "at the pet store downtown", "B": "at Rosamond's creepy house", "C": "at the pond near the woods", "D": "at the park waiting alone"}, "answer": "D", "explanation": "Nate found Fang at the park because 'park' rhymes with 'bark.'"},
    {"id": 15, "difficulty": "hard", "question": "Why does Nate say Fang wasn't really missing?", "options": {"A": "Fang went where he was told", "B": "Fang was hiding as a fun joke", "C": "Fang was never lost at all", "D": "Annie lied about Fang leaving"}, "answer": "A", "explanation": "Nate says Fang followed the command he thought he heard. It was Annie and Harry who were 'missing' from where Fang expected them."},
    {"id": 16, "difficulty": "hard", "question": "What detective lesson does this story teach about clues?", "options": {"A": "Every single clue is important", "B": "Some clues are just red herrings", "C": "Follow everyone that you see", "D": "Never trust any of your friends"}, "answer": "B", "explanation": "The lady in the green hat seemed like a clue but wasn't - she was a red herring. The real clue was the rhyming commands."},
    {"id": 17, "difficulty": "hard", "question": "What does Nate mean when he says 'put yourself in a dog's shoes'?", "options": {"A": "Dogs should always wear shoes", "B": "Dogs are smarter than humans", "C": "Think about why a dog would act", "D": "Shoes can be important clues"}, "answer": "C", "explanation": "Nate means detectives should try to understand the missing person's or animal's point of view."},
    {"id": 18, "difficulty": "hard", "question": "Why was Fang asleep when Nate found him at the park?", "options": {"A": "He was very tired from running", "B": "Someone gave him sleep medicine", "C": "It was already late at night", "D": "He waited for Annie to come"}, "answer": "D", "explanation": "Fang went where he thought he was told and waited for Annie and Harry, so he fell asleep waiting."},
    {"id": 19, "difficulty": "hard", "question": "Why does Nate say 'pancakes help him think'?", "options": {"A": "Pancakes have magic ingredients", "B": "His mother always told him so", "C": "He thinks best while eating them", "D": "Pancakes give him superpowers"}, "answer": "C", "explanation": "Nate takes time to eat and think calmly, and pancakes are his favorite food that helps him focus."},
    {"id": 20, "difficulty": "hard", "question": "What is the main lesson about communication in this story?", "options": {"A": "Never talk to any strangers", "B": "Dogs cannot understand humans", "C": "Parties are very distracting", "D": "Words can cause misunderstandings"}, "answer": "D", "explanation": "The whole mystery happened because Annie said 'bark' meaning to shoo poodles, but Fang heard it as a command rhyming with 'park.'"}
  ]
}
